libreyolo/__init__.py
libreyolo/factory.py
libreyolo/cfg/__init__.py
libreyolo/common/base_model.py
libreyolo/common/image_loader.py
libreyolo/common/onnx.py
libreyolo/common/utils.py
libreyolo/common/postprocessing/__init__.py
libreyolo/common/postprocessing/base.py
libreyolo/common/postprocessing/box_utils.py
libreyolo/common/postprocessing/diou_nms.py
libreyolo/common/postprocessing/nms.py
libreyolo/common/postprocessing/soft_nms.py
libreyolo/data/__init__.py
libreyolo/data/utils.py
libreyolo/data/yolo_coco_api.py
libreyolo/rfdetr/__init__.py
libreyolo/rfdetr/model.py
libreyolo/rfdetr/nn.py
libreyolo/rfdetr/train.py
libreyolo/rfdetr/utils.py
libreyolo/training/__init__.py
libreyolo/training/augment.py
libreyolo/training/config.py
libreyolo/training/dataset.py
libreyolo/training/ema.py
libreyolo/training/loss.py
libreyolo/training/scheduler.py
libreyolo/training/train.py
libreyolo/training/trainer.py
libreyolo/utils/__init__.py
libreyolo/utils/downloads.py
libreyolo/v11/model.py
libreyolo/v11/nn.py
libreyolo/v11/utils.py
libreyolo/v8/model.py
libreyolo/v8/nn.py
libreyolo/v8/utils.py
libreyolo/v9/__init__.py
libreyolo/v9/model.py
libreyolo/v9/nn.py
libreyolo/v9/utils.py
libreyolo/validation/__init__.py
libreyolo/validation/base.py
libreyolo/validation/coco_evaluator.py
libreyolo/validation/config.py
libreyolo/validation/detection_validator.py
libreyolo/validation/metrics.py
libreyolo/validation/preprocessors.py
libreyolo/validation/utils.py
libreyolo/yolox/__init__.py
libreyolo/yolox/model.py
libreyolo/yolox/nn.py
libreyolo/yolox/utils.py
libreyolo-0.1.4.dist-info/licenses/LICENSE
libreyolo-0.1.4.dist-info/METADATA
libreyolo-0.1.4.dist-info/WHEEL
libreyolo-0.1.4.dist-info/top_level.txt
libreyolo-0.1.4.dist-info/RECORD
