Metadata-Version: 2.4
Name: libreyolo
Version: 0.1.4
Summary: Libre YOLO - An open source YOLO library with MIT license.
Author: LibreYOLO Team
License: MIT
Project-URL: Homepage, https://github.com/Libre-YOLO
Project-URL: Repository, https://github.com/Libre-YOLO/libreyolo
Requires-Python: >=3.10
License-File: LICENSE
Requires-Dist: numpy>=1.19.0
Requires-Dist: Pillow>=8.0.0
Requires-Dist: torch>=1.7.0
Requires-Dist: torchvision>=0.11.0
Requires-Dist: PyYAML>=6.0
Requires-Dist: matplotlib>=3.3.0
Requires-Dist: requests>=2.25.0
Requires-Dist: opencv-python>=4.11.0.86
Requires-Dist: tqdm>=4.65.0
Provides-Extra: convert
Requires-Dist: ultralytics; extra == "convert"
Provides-Extra: onnx
Requires-Dist: onnx>=1.14.0; extra == "onnx"
Requires-Dist: onnxscript>=0.1.0; extra == "onnx"
Requires-Dist: onnxruntime>=1.16.0; extra == "onnx"
Provides-Extra: rfdetr
Requires-Dist: rfdetr; extra == "rfdetr"
Requires-Dist: timm>=0.9.0; extra == "rfdetr"
Requires-Dist: supervision>=0.19.0; extra == "rfdetr"
Dynamic: license-file
